dataknobs_xization/0.readme.txt
dataknobs_xization/__init__.py
dataknobs_xization/annotations.py
dataknobs_xization/authorities.py
dataknobs_xization/content_transformer.py
dataknobs_xization/lexicon.py
dataknobs_xization/masking_tokenizer.py
dataknobs_xization/normalize.py
dataknobs_xization/py.typed
dataknobs_xization/ingestion/__init__.py
dataknobs_xization/ingestion/config.py
dataknobs_xization/ingestion/processor.py
dataknobs_xization/json/__init__.py
dataknobs_xization/json/json_chunker.py
dataknobs_xization/markdown/__init__.py
dataknobs_xization/markdown/enrichment.py
dataknobs_xization/markdown/filters.py
dataknobs_xization/markdown/md_chunker.py
dataknobs_xization/markdown/md_parser.py
dataknobs_xization/markdown/md_streaming.py
dataknobs_xization-1.2.4.dist-info/METADATA
dataknobs_xization-1.2.4.dist-info/WHEEL
dataknobs_xization-1.2.4.dist-info/RECORD
