Metadata-Version: 2.4
Name: dataknobs-xization
Version: 1.2.4
Summary: Text normalization and tokenization tools
Author-email: Spence Koehler <KoehlerSB747@gmail.com>
Requires-Python: >=3.10
Requires-Dist: dataknobs-common>=1.0.0
Requires-Dist: dataknobs-structures>=1.0.0
Requires-Dist: dataknobs-utils>=1.0.0
Requires-Dist: more-itertools>=8.10.0
Requires-Dist: nltk>=3.9.1
